ort/__init__.py
ort/conlib.py
ort/libort.so
ort-1.2.1.dist-info/METADATA
ort-1.2.1.dist-info/WHEEL
ort-1.2.1.dist-info/top_level.txt
ort-1.2.1.dist-info/RECORD
